metagraph_katana/__init__.py
metagraph_katana/plugins/__init__.py
metagraph_katana/plugins/metagraph_katana/__init__.py
metagraph_katana/plugins/metagraph_katana/algorithms.py
metagraph_katana/plugins/metagraph_katana/translators.py
metagraph_katana/plugins/metagraph_katana/types.py
metagraph_katana/tests/__init__.py
metagraph_katana/tests/conftest.py
metagraph_katana/tests/test_algorithms.py
metagraph_katana/tests/test_translators.py
metagraph_katana/tests/test_types.py
metagraph_katana-0.1.2.dist-info/LICENSE.txt
metagraph_katana-0.1.2.dist-info/METADATA
metagraph_katana-0.1.2.dist-info/WHEEL
metagraph_katana-0.1.2.dist-info/entry_points.txt
metagraph_katana-0.1.2.dist-info/top_level.txt
metagraph_katana-0.1.2.dist-info/RECORD
